helga_contrib_updates
