Metadata-Version: 1.1
Name: helga-contrib-updates
Version: 1.0.3
Summary: A helga plugin to list and record IRC channel updates.
Home-page: https://github.com/cobbdb/helga-contrib-updates
Author: Dan Cobb, Shaun Duncan
Author-email: cobbdb@gmail.com, shaun.duncan@gmail.com
License: MIT
Keywords: helga plugin irc standup
Platform: UNKNOWN
Classifier: Development Status :: 5 - Production/Stable
Classifier: Intended Audience :: Developers
Classifier: Intended Audience :: Information Technology
Classifier: License :: OSI Approved :: MIT License
Classifier: Operating System :: OS Independent
Classifier: Natural Language :: English
Classifier: Programming Language :: Python :: 2.6
Classifier: Programming Language :: Python :: 2.7
Classifier: Programming Language :: Python :: 3.3
Classifier: Topic :: Communications :: Chat
Classifier: Topic :: Communications :: Chat :: Internet Relay Chat
Classifier: Topic :: Software Development
